pyhap/__init__.py
pyhap/accessory.py
pyhap/accessory_driver.py
pyhap/camera.py
pyhap/characteristic.py
pyhap/const.py
pyhap/encoder.py
pyhap/hap_crypto.py
pyhap/hap_event.py
pyhap/hap_handler.py
pyhap/hap_protocol.py
pyhap/hap_server.py
pyhap/hsrp.py
pyhap/iid_manager.py
pyhap/loader.py
pyhap/params.py
pyhap/service.py
pyhap/state.py
pyhap/tlv.py
pyhap/util.py
pyhap/resources/characteristics.json
pyhap/resources/services.json
pyhap/resources/snapshot.jpg
HAP_python-4.9.2.dist-info/LICENSE
HAP_python-4.9.2.dist-info/METADATA
HAP_python-4.9.2.dist-info/WHEEL
HAP_python-4.9.2.dist-info/top_level.txt
HAP_python-4.9.2.dist-info/RECORD
