Metadata-Version: 2.1
Name: HAP-python
Version: 4.9.2
Summary: HomeKit Accessory Protocol implementation in python
Home-page: https://github.com/ikalchev/HAP-python
License: Apache License 2.0
Project-URL: Bug Reports, https://github.com/ikalchev/HAP-python/issues
Project-URL: Documentation, http://hap-python.readthedocs.io/en/latest/
Project-URL: Source, https://github.com/ikalchev/HAP-python/tree/master
Classifier: Development Status :: 5 - Production/Stable
Classifier: Intended Audience :: Developers
Classifier: Intended Audience :: End Users/Desktop
Classifier: License :: OSI Approved :: Apache Software License
Classifier: Natural Language :: English
Classifier: Operating System :: OS Independent
Classifier: Programming Language :: Python :: 3.5
Classifier: Programming Language :: Python :: 3.6
Classifier: Programming Language :: Python :: 3.7
Classifier: Programming Language :: Python :: 3.8
Classifier: Programming Language :: Python :: 3.9
Classifier: Programming Language :: Python :: 3.10
Classifier: Topic :: Home Automation
Classifier: Topic :: Software Development :: Libraries :: Python Modules
Requires-Python: >=3.7
License-File: LICENSE
Requires-Dist: async_timeout
Requires-Dist: cryptography
Requires-Dist: chacha20poly1305-reuseable
Requires-Dist: orjson>=3.7.2
Requires-Dist: zeroconf>=0.36.2
Requires-Dist: h11
Provides-Extra: qrcode
Requires-Dist: base36; extra == "qrcode"
Requires-Dist: pyqrcode; extra == "qrcode"
